async_polygon/__init__.py
async_polygon/rest/__init__.py
async_polygon/rest/client.py
async_polygon/rest/dataclasses/__init__.py
async_polygon/rest/dataclasses/pretty_json.py
async_polygon/rest/dataclasses/templates.py
async_polygon-0.0.0a3.dist-info/LICENSE
async_polygon-0.0.0a3.dist-info/METADATA
async_polygon-0.0.0a3.dist-info/WHEEL
async_polygon-0.0.0a3.dist-info/top_level.txt
async_polygon-0.0.0a3.dist-info/RECORD
