Metadata-Version: 2.1
Name: async-polygon
Version: 0.0.0a3
Summary: Async Polygon REST API
Home-page: https://github.com/mirage-deadline/async-polygon
Author: Dmitry Skripka
Author-email: dmitrio.skripka@gmail.com
License: UNKNOWN
Platform: UNKNOWN
Classifier: License :: OSI Approved :: MIT License
Classifier: Programming Language :: Python :: 3
Classifier: Operating System :: OS Independent
Classifier: Topic :: Office/Business :: Financial :: Investment
License-File: LICENSE
Requires-Dist: aiohttp (>=3.8.1)
Requires-Dist: pandas (==1.4.2)
